README.txt
setup.py
collective/__init__.py
collective.js.gritter.egg-info/PKG-INFO
collective.js.gritter.egg-info/SOURCES.txt
collective.js.gritter.egg-info/dependency_links.txt
collective.js.gritter.egg-info/entry_points.txt
collective.js.gritter.egg-info/namespace_packages.txt
collective.js.gritter.egg-info/not-zip-safe
collective.js.gritter.egg-info/requires.txt
collective.js.gritter.egg-info/top_level.txt
collective/js/__init__.py
collective/js/gritter/__init__.py
collective/js/gritter/configure.zcml
collective/js/gritter/profiles/default/cssregistry.xml
collective/js/gritter/profiles/default/jsregistry.xml
collective/js/gritter/profiles/default/metadata.xml
collective/js/gritter/resources/gritter-close-ie6.gif
collective/js/gritter/resources/gritter-long.png
collective/js/gritter/resources/gritter.png
collective/js/gritter/resources/jquery.gritter.css
collective/js/gritter/resources/jquery.gritter.min.js
docs/HISTORY.txt
docs/INSTALL.txt
docs/LICENSE.GPL
docs/LICENSE.txt