Metadata-Version: 1.0
Name: collective.js.gritter
Version: 1.0.2
Summary: jQuery Gritter (Growl-like-notification) plugin for Plone
Home-page: http://pypi.python.org/pypi/collective.js.gritter
Author: Radim Novotny
Author-email: novotny.radim@gmail.com
License: GPL
Keywords: jquery plone notification growl
Platform: UNKNOWN
Classifier: Framework :: Plone
Classifier: Programming Language :: Python
